[
  {
    "tick": 1000,
    "alive_seconds": 50.0,
    "inputs": {
      "health": 15.0,
      "food": 0.0,
      "slot1_id": 38.0,
      "slot2_id": 17.0,
      "slot3_id": 16.0,
      "slot4_id": 18.0,
      "slot5_id": -1.0,
      "slot6_id": -1.0,
      "slot7_id": -1.0,
      "slot8_id": -1.0,
      "slot9_id": -1.0,
      "slot1_count": 3.0,
      "slot2_count": 5.0,
      "slot3_count": 4.0,
      "slot4_count": 2.0,
      "slot5_count": 0.0,
      "slot6_count": 0.0,
      "slot7_count": 0.0,
      "slot8_count": 0.0,
      "slot9_count": 0.0,
      "held_id": 17.0,
      "held_count": 5.0,
      "eating": 0.0
    },
    "probs": {
      "use_eat": 0.0001996,
      "hotbar_1": 0.0001996,
      "hotbar_2": 0.0001996,
      "hotbar_3": 0.0001996,
      "hotbar_4": 0.0001996,
      "hotbar_5": 0.0001996,
      "hotbar_6": 0.0001996,
      "hotbar_7": 0.0001996,
      "hotbar_8": 0.0001996,
      "hotbar_9": 0.0001996,
      "stand_still": 0.99800395
    },
    "chosen": "stand_still"
  },
  {
    "tick": 2000,
    "alive_seconds": 97.8,
    "inputs": {
      "health": 3.0,
      "food": 0.0,
      "slot1_id": 38.0,
      "slot2_id": 17.0,
      "slot3_id": 16.0,
      "slot4_id": 18.0,
      "slot5_id": -1.0,
      "slot6_id": -1.0,
      "slot7_id": -1.0,
      "slot8_id": -1.0,
      "slot9_id": -1.0,
      "slot1_count": 3.0,
      "slot2_count": 5.0,
      "slot3_count": 4.0,
      "slot4_count": 2.0,
      "slot5_count": 0.0,
      "slot6_count": 0.0,
      "slot7_count": 0.0,
      "slot8_count": 0.0,
      "slot9_count": 0.0,
      "held_id": -1.0,
      "held_count": 0.0,
      "eating": 0.0
    },
    "probs": {
      "use_eat": 0.0001996,
      "hotbar_1": 0.0001996,
      "hotbar_2": 0.0001996,
      "hotbar_3": 0.0001996,
      "hotbar_4": 0.0001996,
      "hotbar_5": 0.0001996,
      "hotbar_6": 0.0001996,
      "hotbar_7": 0.0001996,
      "hotbar_8": 0.0001996,
      "hotbar_9": 0.0001996,
      "stand_still": 0.99800398
    },
    "chosen": "stand_still"
  }
]