[
  {
    "tick": 1579,
    "obs": 500,
    "input_level": 5,
    "action_level": 6,
    "ids": [
      1,
      1,
      1,
      1,
      1,
      1,
      1,
      1,
      1,
      1,
      1,
      1,
      1,
      1,
      1,
      1,
      1,
      2,
      1,
      1,
      1,
      1,
      2,
      1,
      1,
      2,
      2,
      2,
      2,
      2,
      2,
      40,
      2,
      2,
      2,
      50,
      50,
      50,
      2,
      2,
      50,
      50,
      50,
      40,
      2,
      50,
      50,
      50,
      2,
      2,
      22,
      22,
      22,
      22,
      4,
      22,
      22,
      22,
      22,
      22,
      4,
      22,
      4,
      22,
      22,
      22,
      4,
      22,
      22,
      22,
      4,
      22,
      4,
      22,
      22,
      22,
      22,
      22,
      22,
      22,
      22,
      22,
      22,
      22,
      22,
      22,
      22,
      22,
      22,
      22,
      22,
      22,
      22,
      22,
      22,
      22,
      22,
      22,
      22,
      22,
      37,
      10,
      7,
      34,
      19,
      28,
      24,
      17,
      25,
      34,
      48,
      47,
      49,
      54,
      0,
      0,
      0,
      0
    ],
    "raw": [
      19.0,
      0.0,
      1.96,
      5.0,
      -0.0,
      88.76,
      0.0,
      3.0,
      3.0,
      1.0,
      1.0,
      4.0,
      5.0,
      1.0,
      1.0,
      2.0,
      1.0,
      0.0,
      0.0,
      0.0,
      0.0,
      0.0,
      0.0,
      0.0,
      0.0,
      1.0,
      0.08,
      2.0,
      20.0,
      1.0,
      -3.96,
      0.0,
      20.0,
      1.0,
      -1.96,
      -3.61,
      11.0,
      1.0,
      -1.95,
      -0.43,
      2.0,
      0.0,
      0.0,
      0.0,
      0.0,
      0.0,
      0.0,
      0.0,
      0.0,
      0.0,
      0.0,
      0.0,
      0.0,
      0.0,
      0.0,
      0.0,
      0.0
    ],
    "probs": {
      "W_forward": 0.000978,
      "S_backward": 0.000978,
      "A_strafe_left": 0.000978,
      "D_strafe_right": 0.000978,
      "turn_left": 0.000978,
      "turn_right": 0.000978,
      "look_up": 0.000978,
      "look_down": 0.000978,
      "jump": 0.000978,
      "crouch": 0.000978,
      "use_eat": 0.000978,
      "attack": 0.000978,
      "Q_throw": 0.000978,
      "hotbar_1": 0.000978,
      "hotbar_2": 0.000978,
      "hotbar_3": 0.000978,
      "hotbar_4": 0.978473,
      "hotbar_5": 0.000978,
      "hotbar_6": 0.000978,
      "hotbar_7": 0.000978,
      "hotbar_8": 0.000978,
      "hotbar_9": 0.000978,
      "stand_still": 0.000978
    },
    "chosen": "hotbar_4"
  },
  {
    "tick": 3174,
    "obs": 1000,
    "input_level": 5,
    "action_level": 6,
    "ids": [
      1,
      1,
      1,
      1,
      1,
      1,
      1,
      1,
      1,
      1,
      1,
      1,
      1,
      1,
      1,
      1,
      1,
      2,
      1,
      1,
      1,
      1,
      2,
      1,
      1,
      2,
      2,
      2,
      2,
      2,
      2,
      40,
      2,
      2,
      2,
      50,
      50,
      50,
      2,
      2,
      50,
      50,
      50,
      40,
      2,
      50,
      50,
      50,
      2,
      2,
      22,
      22,
      22,
      22,
      4,
      22,
      22,
      22,
      22,
      22,
      4,
      22,
      4,
      22,
      22,
      22,
      4,
      22,
      22,
      22,
      4,
      22,
      4,
      22,
      22,
      22,
      22,
      22,
      22,
      22,
      22,
      22,
      22,
      22,
      22,
      22,
      22,
      22,
      22,
      22,
      22,
      22,
      22,
      22,
      22,
      22,
      22,
      22,
      22,
      22,
      37,
      10,
      7,
      34,
      19,
      28,
      24,
      17,
      25,
      34,
      49,
      47,
      48,
      1,
      0,
      0,
      0,
      0
    ],
    "raw": [
      13.0,
      0.0,
      1.96,
      5.0,
      -0.0,
      19.21,
      0.0,
      3.0,
      3.0,
      1.0,
      1.0,
      4.0,
      5.0,
      1.0,
      1.0,
      2.0,
      1.0,
      0.0,
      0.0,
      0.0,
      0.0,
      0.0,
      0.0,
      1.0,
      0.0,
      1.0,
      -1.96,
      -0.47,
      1.0,
      1.0,
      -3.96,
      0.0,
      18.0,
      1.0,
      -0.01,
      8.06,
      20.0,
      1.0,
      0.25,
      2.58,
      1.0,
      0.0,
      0.0,
      0.0,
      0.0,
      0.0,
      0.0,
      0.0,
      0.0,
      0.0,
      0.0,
      0.0,
      0.0,
      0.0,
      0.0,
      0.0,
      0.0
    ],
    "probs": {
      "W_forward": 0.000978,
      "S_backward": 0.000978,
      "A_strafe_left": 0.000978,
      "D_strafe_right": 0.000978,
      "turn_left": 0.000978,
      "turn_right": 0.000978,
      "look_up": 0.000978,
      "look_down": 0.000978,
      "jump": 0.000978,
      "crouch": 0.000978,
      "use_eat": 0.000978,
      "attack": 0.000978,
      "Q_throw": 0.000978,
      "hotbar_1": 0.000978,
      "hotbar_2": 0.000978,
      "hotbar_3": 0.000978,
      "hotbar_4": 0.978473,
      "hotbar_5": 0.000978,
      "hotbar_6": 0.000978,
      "hotbar_7": 0.000978,
      "hotbar_8": 0.000978,
      "hotbar_9": 0.000978,
      "stand_still": 0.000978
    },
    "chosen": "hotbar_4"
  },
  {
    "tick": 4762,
    "obs": 1500,
    "input_level": 5,
    "action_level": 6,
    "ids": [
      1,
      1,
      1,
      1,
      1,
      1,
      1,
      1,
      1,
      1,
      1,
      2,
      1,
      1,
      1,
      2,
      1,
      2,
      1,
      1,
      1,
      1,
      2,
      1,
      1,
      2,
      2,
      2,
      2,
      2,
      2,
      40,
      2,
      2,
      2,
      50,
      50,
      50,
      2,
      2,
      50,
      50,
      50,
      40,
      2,
      50,
      50,
      50,
      2,
      2,
      22,
      22,
      22,
      22,
      4,
      22,
      22,
      22,
      22,
      22,
      4,
      22,
      4,
      22,
      22,
      22,
      4,
      22,
      22,
      22,
      4,
      22,
      4,
      22,
      22,
      22,
      22,
      22,
      22,
      22,
      22,
      22,
      22,
      22,
      22,
      22,
      22,
      22,
      22,
      22,
      22,
      22,
      22,
      22,
      22,
      22,
      22,
      22,
      22,
      22,
      37,
      10,
      7,
      0,
      19,
      28,
      24,
      17,
      25,
      25,
      49,
      47,
      48,
      1,
      34,
      0,
      0,
      0
    ],
    "raw": [
      7.0,
      0.0,
      1.96,
      5.0,
      -0.0,
      1.93,
      0.0,
      3.0,
      3.0,
      1.0,
      0.0,
      4.0,
      5.0,
      1.0,
      1.0,
      2.0,
      2.0,
      1.0,
      0.0,
      0.0,
      0.0,
      0.0,
      0.0,
      1.0,
      0.0,
      1.0,
      -1.96,
      -0.47,
      14.33,
      1.0,
      -3.96,
      0.0,
      12.0,
      1.0,
      -0.03,
      8.08,
      15.0,
      1.0,
      0.25,
      2.58,
      1.0,
      1.0,
      -0.04,
      3.65,
      1.0,
      0.0,
      0.0,
      0.0,
      0.0,
      0.0,
      0.0,
      0.0,
      0.0,
      0.0,
      0.0,
      0.0,
      0.0
    ],
    "probs": {
      "W_forward": 0.000978,
      "S_backward": 0.000978,
      "A_strafe_left": 0.000978,
      "D_strafe_right": 0.000978,
      "turn_left": 0.000978,
      "turn_right": 0.000978,
      "look_up": 0.000978,
      "look_down": 0.000978,
      "jump": 0.000978,
      "crouch": 0.000978,
      "use_eat": 0.978473,
      "attack": 0.000978,
      "Q_throw": 0.000978,
      "hotbar_1": 0.000978,
      "hotbar_2": 0.000978,
      "hotbar_3": 0.000978,
      "hotbar_4": 0.000978,
      "hotbar_5": 0.000978,
      "hotbar_6": 0.000978,
      "hotbar_7": 0.000978,
      "hotbar_8": 0.000978,
      "hotbar_9": 0.000978,
      "stand_still": 0.000978
    },
    "chosen": "use_eat"
  }
]